LICENSE
README.md
setup.py
DjangoComponents/__init__.py
DjangoComponents/management/__init__.py
DjangoComponents/management/commands/__init__.py
DjangoComponents/management/commands/createcomponent.py
componentsDjango34.egg-info/PKG-INFO
componentsDjango34.egg-info/SOURCES.txt
componentsDjango34.egg-info/dependency_links.txt
componentsDjango34.egg-info/entry_points.txt
componentsDjango34.egg-info/requires.txt
componentsDjango34.egg-info/top_level.txt