Metadata-Version: 2.1
Name: componentsDjango34
Version: 0.0.1
Summary: Este paquete se instala en Django para proporcionar componentes HTML y otras funcionalidades.
Home-page: https://github.com/jose-CR/Django-components
Author: Alejandro
License: UNKNOWN
Platform: UNKNOWN
Classifier: Framework :: Django
Classifier: Programming Language :: Python :: 3
Classifier: License :: OSI Approved :: MIT License
Classifier: Operating System :: OS Independent
Requires-Python: >=3.6
License-File: LICENSE
